PyMailMan
