Metadata-Version: 1.0
Name: PyMailMan
Version: 0.9.2
Summary: A simple tool for sending mail by Python
Home-page: UNKNOWN
Author: kongkongyzt
Author-email: kongkongyzt@gmail.com
License: MIT License
Keywords: mail,smtp
Platform: any
